dislib/__init__.py
dislib/classification/__init__.py
dislib/classification/csvm/__init__.py
dislib/classification/csvm/base.py
dislib/classification/knn/__init__.py
dislib/classification/knn/base.py
dislib/cluster/__init__.py
dislib/cluster/daura/__init__.py
dislib/cluster/daura/base.py
dislib/cluster/dbscan/__init__.py
dislib/cluster/dbscan/base.py
dislib/cluster/dbscan/classes.py
dislib/cluster/gm/__init__.py
dislib/cluster/gm/base.py
dislib/cluster/kmeans/__init__.py
dislib/cluster/kmeans/base.py
dislib/data/__init__.py
dislib/data/array.py
dislib/data/io.py
dislib/data/util/__init__.py
dislib/data/util/base.py
dislib/data/util/model.py
dislib/decomposition/__init__.py
dislib/decomposition/pca/__init__.py
dislib/decomposition/pca/base.py
dislib/decomposition/qr/__init__.py
dislib/decomposition/qr/base.py
dislib/decomposition/tsqr/__init__.py
dislib/decomposition/tsqr/base.py
dislib/math/__init__.py
dislib/math/base.py
dislib/model_selection/__init__.py
dislib/model_selection/_search.py
dislib/model_selection/_simulation.py
dislib/model_selection/_split.py
dislib/model_selection/_validation.py
dislib/neighbors/__init__.py
dislib/neighbors/base.py
dislib/optimization/__init__.py
dislib/optimization/admm/__init__.py
dislib/optimization/admm/base.py
dislib/preprocessing/__init__.py
dislib/preprocessing/minmax_scaler.py
dislib/preprocessing/standard_scaler.py
dislib/recommendation/__init__.py
dislib/recommendation/als/__init__.py
dislib/recommendation/als/base.py
dislib/regression/__init__.py
dislib/regression/lasso/__init__.py
dislib/regression/lasso/base.py
dislib/regression/linear/__init__.py
dislib/regression/linear/base.py
dislib/trees/__init__.py
dislib/trees/data.py
dislib/trees/decision_tree.py
dislib/trees/forest.py
dislib/trees/test_split.py
dislib/utils/__init__.py
dislib/utils/base.py
dislib-0.8.0.dist-info/LICENSE
dislib-0.8.0.dist-info/METADATA
dislib-0.8.0.dist-info/NOTICE
dislib-0.8.0.dist-info/WHEEL
dislib-0.8.0.dist-info/top_level.txt
dislib-0.8.0.dist-info/RECORD
