Metadata-Version: 2.1
Name: dislib
Version: 0.8.0
Summary: The distributed computing library on top of PyCOMPSs
Home-page: http://dislib.bsc.es
Author: Barcelona Supercomputing Center
Author-email: compss@bsc.es
Project-URL: Documentation, http://dislib.bsc.es
Project-URL: Source, https://github.com/bsc-wdc/dislib
Project-URL: Tracker, https://github.com/bsc-wdc/dislib/issues
Classifier: Programming Language :: Python :: 3 :: Only
Classifier: License :: OSI Approved :: Apache Software License
Classifier: Development Status :: 2 - Pre-Alpha
Classifier: Operating System :: POSIX :: Linux
Classifier: Topic :: Scientific/Engineering :: Artificial Intelligence
Classifier: Topic :: Software Development :: Libraries
Classifier: Topic :: Software Development :: Libraries :: Python Modules
Classifier: Topic :: System :: Distributed Computing
License-File: LICENSE
License-File: NOTICE
Requires-Dist: scikit-learn (>=1.0.2)
Requires-Dist: scipy (>=1.3.0)
Requires-Dist: numpy (>=1.18.1)
Requires-Dist: numpydoc (>=0.8.0)
Requires-Dist: cvxpy (>=1.1.5)
Requires-Dist: cbor2 (>=5.4.0)
Requires-Dist: pandas (>=0.24.2)
Requires-Dist: matplotlib (>=2.2.3)
